ltempy/__init__.py
ltempy/_utils.py
ltempy/colors.py
ltempy/constants.py
ltempy/plot.py
ltempy/process.py
ltempy/simulate.py
ltempy/sitie.py
ltempy-1.6.0.dist-info/LICENSE
ltempy-1.6.0.dist-info/METADATA
ltempy-1.6.0.dist-info/WHEEL
ltempy-1.6.0.dist-info/top_level.txt
ltempy-1.6.0.dist-info/RECORD
