Metadata-Version: 2.1
Name: ltempy
Version: 1.6.0
Summary: Utilities for Lorentz TEM data analysis and simulation.
Home-page: https://github.com/McMorranLab/ltempy
Author: William S. Parker
Author-email: will.parker0@gmail.com
Project-URL: Documentation, https://mcmorranlab.github.io/ltempy/
Project-URL: Bug Tracker, https://github.com/McMorranLab/ltempy/issues
Classifier: Programming Language :: Python :: 3
Classifier: License :: OSI Approved :: GNU General Public License v3 (GPLv3)
Classifier: Operating System :: OS Independent
Requires-Python: >=3.6
License-File: LICENSE
Requires-Dist: numpy
Requires-Dist: matplotlib
